hyperspy_gui_ipywidgets/__init__.py
hyperspy_gui_ipywidgets/axes.py
hyperspy_gui_ipywidgets/conftest.py
hyperspy_gui_ipywidgets/custom_widgets.py
hyperspy_gui_ipywidgets/hyperspy_extension.yaml
hyperspy_gui_ipywidgets/microscope_parameters.py
hyperspy_gui_ipywidgets/model.py
hyperspy_gui_ipywidgets/preferences.py
hyperspy_gui_ipywidgets/roi.py
hyperspy_gui_ipywidgets/tools.py
hyperspy_gui_ipywidgets/utils.py
hyperspy_gui_ipywidgets/tests/__init__.py
hyperspy_gui_ipywidgets/tests/test_axes.py
hyperspy_gui_ipywidgets/tests/test_import.py
hyperspy_gui_ipywidgets/tests/test_microscope_parameters.py
hyperspy_gui_ipywidgets/tests/test_model.py
hyperspy_gui_ipywidgets/tests/test_preferences.py
hyperspy_gui_ipywidgets/tests/test_roi.py
hyperspy_gui_ipywidgets/tests/test_tools.py
hyperspy_gui_ipywidgets/tests/utils.py
hyperspy_gui_ipywidgets-2.1.0.dist-info/LICENSE
hyperspy_gui_ipywidgets-2.1.0.dist-info/METADATA
hyperspy_gui_ipywidgets-2.1.0.dist-info/WHEEL
hyperspy_gui_ipywidgets-2.1.0.dist-info/entry_points.txt
hyperspy_gui_ipywidgets-2.1.0.dist-info/top_level.txt
hyperspy_gui_ipywidgets-2.1.0.dist-info/RECORD
